.DS_Store
src/config.py
src/exfunc.py
src/yatcx_parser.py
yatcxparser/__init__.py
yatcxparser/config.py
yatcxparser/exfunc.py
yatcxparser/yatcx_parser.py
yatcxparser-0.0.1b0.dist-info/LICENSE
yatcxparser-0.0.1b0.dist-info/METADATA
yatcxparser-0.0.1b0.dist-info/WHEEL
yatcxparser-0.0.1b0.dist-info/top_level.txt
yatcxparser-0.0.1b0.dist-info/RECORD
