Metadata-Version: 2.1
Name: yatcxparser
Version: 0.0.1b0
Summary: Simple parser for advanced analytics of the Garmin TCX files
Home-page: https://github.com/alexey-ka/YATCX_parser
Author: Aleksei Karetnikov
Author-email: alexey.karetnikow@gmail.com
License: MIT
Keywords: tcx
Platform: UNKNOWN
Classifier: Development Status :: 4 - Beta
Classifier: Intended Audience :: Developers
Classifier: License :: OSI Approved :: MIT License
Classifier: Operating System :: OS Independent
Classifier: Programming Language :: Python
Classifier: Programming Language :: Python :: 3
Classifier: Programming Language :: Python :: 3.6
Classifier: Programming Language :: Python :: 3.7
Classifier: Programming Language :: Python :: 3.8
Classifier: Programming Language :: Python :: 3.9
Classifier: Topic :: Software Development :: Libraries :: Python Modules
Requires-Dist: lxml
Requires-Dist: numpy
